optigatrust/DESCRIPTION.md
optigatrust/__init__.py
optigatrust/__main__.py
optigatrust/_backend.py
optigatrust/clidriver.py
optigatrust/crypto.py
optigatrust/csr.py
optigatrust/objects.py
optigatrust/port.py
optigatrust/util.py
optigatrust/version.py
optigatrust/enums/__init__.py
optigatrust/enums/charge.py
optigatrust/enums/conf_template.xml
optigatrust/enums/m1.py
optigatrust/enums/m2id2.py
optigatrust/enums/m3.py
optigatrust/enums/x.py
optigatrust/lib/liboptigatrust-i2c-gpiod-linux-aarch64.so
optigatrust/lib/liboptigatrust-i2c-gpiod-linux-armv7l.so
optigatrust/lib/liboptigatrust-i2c-gpiod-linux-x86_64.so
optigatrust/lib/liboptigatrust-i2c-linux-aarch64.so
optigatrust/lib/liboptigatrust-i2c-linux-armv7l.so
optigatrust/lib/liboptigatrust-i2c-linux-x86_64.so
optigatrust/lib/liboptigatrust-libusb-linux-aarch64.so
optigatrust/lib/liboptigatrust-libusb-linux-armv7l.so
optigatrust/lib/liboptigatrust-libusb-linux-x86_64.so
optigatrust/lib/liboptigatrust-libusb-win-amd64.dll
optigatrust/lib/liboptigatrust-libusb-win-i686.dll
optigatrust/lib/liboptigatrust-uart-linux-aarch64.so
optigatrust/lib/liboptigatrust-uart-linux-armv7l.so
optigatrust/lib/liboptigatrust-uart-linux-x86_64.so
optigatrust/lib/liboptigatrust-uart-win-amd64.dll
optigatrust/lib/liboptigatrust-uart-win-i686.dll
optigatrust/rules/90-optigatrust.rules
optigatrust-1.5.1.dist-info/licenses/LICENSE
optigatrust-1.5.1.dist-info/METADATA
optigatrust-1.5.1.dist-info/WHEEL
optigatrust-1.5.1.dist-info/entry_points.txt
optigatrust-1.5.1.dist-info/top_level.txt
optigatrust-1.5.1.dist-info/RECORD
