Metadata-Version: 2.4
Name: optigatrust
Version: 1.5.1
Summary: A ctypes based Python wrapper for the OPTIGA™ Trust M Host Library for C
Home-page: https://github.com/infineon/python-optiga-trust
Author: Infineon Technologies AG
Author-email: dsi-host-software@infineon.com
License: MIT
Keywords: ECDHE ECDSA RSA ECC X509 NISTP256 NIST384 OPTIGA TRUST TRUSTX TRUSTM
Classifier: Development Status :: 5 - Production/Stable
Classifier: License :: OSI Approved :: MIT License
Classifier: Intended Audience :: Developers
Classifier: Programming Language :: Python
Classifier: Operating System :: Microsoft :: Windows
Classifier: Operating System :: POSIX :: Linux
Classifier: Framework :: Pytest
Requires-Python: >=3.5
License-File: LICENSE
Requires-Dist: optigatrust
Requires-Dist: asn1crypto
Requires-Dist: jinja2
Requires-Dist: cryptography
Requires-Dist: pyserial
Requires-Dist: click
Dynamic: author
Dynamic: author-email
Dynamic: classifier
Dynamic: description
Dynamic: description-content-type
Dynamic: home-page
Dynamic: keywords
Dynamic: license
Dynamic: license-file
Dynamic: requires-dist
Dynamic: requires-python
Dynamic: summary
